_efoli_version.py
efoli/__init__.py
efoli/edifact_format.py
efoli/edifact_format_version.py
efoli/py.typed
efoli/strenum.py
efoli-2.1.1.dist-info/METADATA
efoli-2.1.1.dist-info/WHEEL
efoli-2.1.1.dist-info/RECORD
