Metadata-Version: 2.4
Name: efoli
Version: 2.1.1
Summary: Enums and related helper functions that model EDIFACT relevant data for German utilities
Project-URL: Changelog, https://github.com/Hochfrequenz/efoli/releases
Project-URL: Homepage, https://github.com/Hochfrequenz/efoli
Author-email: Hochfrequenz Unternehmensberatung GmbH <info+github@hochfrequenz.de>
License: MIT
Keywords: bdew,edifact,enums
Classifier: Development Status :: 5 - Production/Stable
Classifier: Environment :: Console
Classifier: Intended Audience :: Developers
Classifier: License :: OSI Approved :: MIT License
Classifier: Operating System :: OS Independent
Classifier: Programming Language :: Python
Classifier: Programming Language :: Python :: 3 :: Only
Classifier: Programming Language :: Python :: 3.9
Classifier: Programming Language :: Python :: 3.10
Classifier: Programming Language :: Python :: 3.11
Classifier: Programming Language :: Python :: 3.12
Classifier: Programming Language :: Python :: 3.13
Classifier: Programming Language :: Python :: 3.14
Requires-Python: >=3.9
Requires-Dist: pytz
Provides-Extra: coverage
Requires-Dist: coverage==7.10.7; extra == 'coverage'
Provides-Extra: formatting
Requires-Dist: black==25.9.0; extra == 'formatting'
Requires-Dist: isort==6.1.0; extra == 'formatting'
Provides-Extra: linting
Requires-Dist: pylint==3.3.9; extra == 'linting'
Provides-Extra: packaging
Requires-Dist: build==1.3.0; extra == 'packaging'
Requires-Dist: twine==6.2.0; extra == 'packaging'
Provides-Extra: spellcheck
Requires-Dist: codespell==2.4.1; extra == 'spellcheck'
Provides-Extra: tests
Requires-Dist: pytest==8.4.2; extra == 'tests'
Provides-Extra: type-check
Requires-Dist: mypy==1.18.2; extra == 'type-check'
Requires-Dist: types-pytz==2025.2.0.20250809; extra == 'type-check'
